semaphore_mcp/__init__.py
semaphore_mcp/api.py
semaphore_mcp/config.py
semaphore_mcp/server.py
semaphore_mcp/scripts/__init__.py
semaphore_mcp/scripts/start_server.py
semaphore_mcp/tools/__init__.py
semaphore_mcp/tools/access_keys.py
semaphore_mcp/tools/base.py
semaphore_mcp/tools/environments.py
semaphore_mcp/tools/projects.py
semaphore_mcp/tools/repositories.py
semaphore_mcp/tools/tasks.py
semaphore_mcp/tools/templates.py
semaphore_mcp-1.0.2.dist-info/licenses/LICENSE
semaphore_mcp-1.0.2.dist-info/METADATA
semaphore_mcp-1.0.2.dist-info/WHEEL
semaphore_mcp-1.0.2.dist-info/entry_points.txt
semaphore_mcp-1.0.2.dist-info/top_level.txt
semaphore_mcp-1.0.2.dist-info/RECORD
