Metadata-Version: 2.4
Name: semaphore-mcp
Version: 1.0.2
Summary: Model Context Protocol (MCP) server for SemaphoreUI automation
Author: Colin McNaughton
License: AGPL-3.0-or-later
Project-URL: Homepage, https://github.com/cloin/semaphore-mcp
Project-URL: Bug Tracker, https://github.com/cloin/semaphore-mcp/issues
Project-URL: Documentation, https://github.com/cloin/semaphore-mcp#readme
Project-URL: Source Code, https://github.com/cloin/semaphore-mcp
Keywords: mcp,model-context-protocol,semaphore,ansible,automation,devops
Classifier: Development Status :: 4 - Beta
Classifier: Intended Audience :: Developers
Classifier: Intended Audience :: System Administrators
Classifier: License :: OSI Approved :: GNU Affero General Public License v3 or later (AGPLv3+)
Classifier: Operating System :: OS Independent
Classifier: Programming Language :: Python :: 3
Classifier: Programming Language :: Python :: 3.10
Classifier: Programming Language :: Python :: 3.11
Classifier: Programming Language :: Python :: 3.12
Classifier: Topic :: Software Development :: Libraries :: Python Modules
Classifier: Topic :: System :: Systems Administration
Requires-Python: >=3.10
License-File: LICENSE
Requires-Dist: requests>=2.31.0
Requires-Dist: pydantic>=2.5.0
Requires-Dist: python-dotenv>=1.0.0
Requires-Dist: mcp>=1.9.3
Requires-Dist: aiohttp>=3.8.5
Provides-Extra: dev
Requires-Dist: pytest>=7.4.0; extra == "dev"
Requires-Dist: pytest-asyncio>=0.21.1; extra == "dev"
Requires-Dist: ruff>=0.1.0; extra == "dev"
Requires-Dist: mypy>=1.8.0; extra == "dev"
Requires-Dist: types-requests>=2.31.0; extra == "dev"
Requires-Dist: pre-commit>=3.5.0; extra == "dev"
Provides-Extra: server
Requires-Dist: fastapi>=0.104.0; extra == "server"
Requires-Dist: uvicorn>=0.23.2; extra == "server"
Dynamic: license-file
